wsgi_static_middleware.py
wsgi_static_middleware-0.1.2.dist-info/DESCRIPTION.rst
wsgi_static_middleware-0.1.2.dist-info/METADATA
wsgi_static_middleware-0.1.2.dist-info/RECORD
wsgi_static_middleware-0.1.2.dist-info/WHEEL
wsgi_static_middleware-0.1.2.dist-info/metadata.json
wsgi_static_middleware-0.1.2.dist-info/top_level.txt
