Metadata-Version: 2.0
Name: wsgi-static-middleware
Version: 0.1.2
Summary: WSGI Middleware for serving static files
Home-page: https://github.com/kobinpy/wsgi-static-middleware
Author: Masashi Shibata <contact@c-bata.link>
Author-email: contact@c-bata.link
License: MIT License
Keywords: wsgi middleware staticfile
Platform: UNKNOWN
Classifier: Development Status :: 3 - Alpha
Classifier: Intended Audience :: Developers
Classifier: License :: OSI Approved :: MIT License
Classifier: Topic :: Internet :: WWW/HTTP :: WSGI
Classifier: Topic :: Internet :: WWW/HTTP :: WSGI :: Middleware
Classifier: Programming Language :: Python
Classifier: Programming Language :: Python :: 3
Classifier: Programming Language :: Python :: 3.5
Classifier: Programming Language :: Python :: 3.6
